CHANGELOG.md
LICENSE
MANIFEST.in
Makefile.in
README.md
configure
pyproject.toml
setup.py
sht_com.c
sht_config.h.in
sht_fly.c
sht_func.c
sht_init.c
sht_kernels_a.c
sht_kernels_s.c
sht_legendre.c
sht_odd_nlat.c
sht_omp.c
sht_private.h
shtns.h
shtns.py
shtns_numpy_wrap.c
shtns_simd.h
time_SHT.c
SHT/Makefile
SHT/fly_SH_to_spat.gen.c
SHT/fly_spat_to_SH.gen.c
SHT/kernel_SH_to_spat.gen.c
SHT/kernel_spat_to_SH.gen.c
SHT/omp_SH_to_spat.gen.c
SHT/omp_spat_to_SH.gen.c
fftw3/cycle.h
fftw3/fftw3.h
hiprec/high_precision.h
shtns.egg-info/PKG-INFO
shtns.egg-info/SOURCES.txt
shtns.egg-info/dependency_links.txt
shtns.egg-info/requires.txt
shtns.egg-info/top_level.txt