Metadata-Version: 2.4
Name: shtns
Version: 3.7.4
Summary: High performance Spherical Harmonic Transform
Home-page: https://bitbucket.org/nschaeff/shtns
Author: Nathanael Schaeffer
Author-email: Nathanael Schaeffer <nathanael.schaeffer@gmail.com>
Project-URL: Homepage, https://bitbucket.org/nschaeff/shtns/
Project-URL: Documentation, https://nschaeff.bitbucket.io/shtns/
Project-URL: Repository, https://bitbucket.org/nschaeff/shtns/
Project-URL: Changelog, https://bitbucket.org/nschaeff/shtns/src/master/CHANGELOG.md
Classifier: Programming Language :: C
Classifier: Programming Language :: Python
Classifier: License :: OSI Approved :: CEA CNRS Inria Logiciel Libre License, version 2.1 (CeCILL-2.1)
Classifier: Intended Audience :: Science/Research
Classifier: Development Status :: 5 - Production/Stable
Classifier: Topic :: Scientific/Engineering
Requires: numpy
Requires-Python: >=3.2
License-File: LICENSE
Requires-Dist: numpy
Dynamic: author
Dynamic: home-page
Dynamic: license-file
Dynamic: requires
